<?xml version="1.0" encoding="ISO-8859-1" ?>
<races>
    <race name="LS RoundCurse" laps="3">
        <checkpoint x="2070.2810" y="-1812.499" z="13.038820" />
        <checkpoint x="1968.1876" y="-1812.015" z="13.037757" />
        <checkpoint x="1961.1191" y="-1922.493" z="13.038669" />
        <checkpoint x="1832.9859" y="-1930.360" z="13.039778" />
        <checkpoint x="1821.5600" y="-1839.802" z="13.069824" />
        <checkpoint x="1703.0555" y="-1815.098" z="13.022415" />
        <checkpoint x="1690.2370" y="-1738.875" z="13.043513" />
        <checkpoint x="1689.8438" y="-1600.215" z="13.038777" />
        <checkpoint x="1781.2429" y="-1608.850" z="13.020270" />
        <checkpoint x="1916.7302" y="-1612.015" z="13.038738" />
        <checkpoint x="1940.6324" y="-1691.826" z="13.038748" />
        <checkpoint x="1941.5788" y="-1746.296" z="13.038607" />
        <checkpoint x="1999.3336" y="-1752.780" z="13.039111" />
        <checkpoint x="2079.6833" y="-1753.005" z="13.041625" />
    </race>
    <race name="LS Police Sprint" laps="1">
        <checkpoint x="1528.0500" y="-1730.859" z="13.041275" />
        <checkpoint x="1411.2009" y="-1731.699" z="13.046525" />
        <checkpoint x="1320.1469" y="-1731.696" z="13.038730" />
        <checkpoint x="1311.6429" y="-1606.935" z="13.038806" />
        <checkpoint x="1348.8188" y="-1459.285" z="13.040258" />
        <checkpoint x="1356.4984" y="-1274.141" z="13.031648" />
        <checkpoint x="1353.6861" y="-1146.625" z="23.345663" />
        <checkpoint x="1264.9367" y="-1144.480" z="23.307872" />
        <checkpoint x="1172.2503" y="-1143.180" z="23.318613" />
        <checkpoint x="1163.6112" y="-1044.123" z="31.327257" />
        <checkpoint x="1162.7760" y="-963.9434" z="42.158943" />
        <checkpoint x="1226.6732" y="-939.5665" z="42.234848" />
        <checkpoint x="1363.6500" y="-932.5603" z="33.844593" />
        <checkpoint x="1388.5605" y="-894.5465" z="37.065738" />
        <checkpoint x="1473.3658" y="-876.6511" z="56.509967" />
        <checkpoint x="1517.8095" y="-817.3613" z="70.039352" />
        <checkpoint x="1457.8690" y="-742.7609" z="94.275482" />
        <checkpoint x="1420.4774" y="-694.8889" z="87.145683" />
        <checkpoint x="1286.5249" y="-716.8757" z="92.908683" />
        <checkpoint x="1157.6773" y="-761.9553" z="106.87718" />
        <checkpoint x="1067.5909" y="-774.0213" z="106.66098" />
        <checkpoint x="985.87829" y="-790.9031" z="100.86618" />
        <checkpoint x="946.99676" y="-788.1138" z="107.31791" />
        <checkpoint x="939.69635" y="-762.5159" z="107.20124" />
        <checkpoint x="894.43127" y="-768.1607" z="96.007545" />
        <checkpoint x="833.34191" y="-787.5545" z="73.684013" />
        <checkpoint x="715.73907" y="-817.1312" z="69.959815" />
        <checkpoint x="648.06146" y="-891.2412" z="62.629005" />
        <checkpoint x="546.07379" y="-906.3847" z="69.338256" />
        <checkpoint x="515.03198" y="-956.6464" z="80.495697" />
        <checkpoint x="466.25381" y="-1010.140" z="92.414138" />
        <checkpoint x="334.71545" y="-1031.936" z="92.893180" />
        <checkpoint x="270.01052" y="-1115.619" z="78.883743" />
        <checkpoint x="220.18501" y="-1145.255" z="62.998481" />
        <checkpoint x="136.09869" y="-1261.784" z="45.414039" />
        <checkpoint x="143.41705" y="-1366.871" z="49.606864" />
        <checkpoint x="165.90007" y="-1401.108" z="46.568092" />
        <checkpoint x="96.162315" y="-1523.355" z="5.367919" />
        <checkpoint x="140.00587" y="-1551.353" z="9.239809" />
        <checkpoint x="210.15913" y="-1484.339" z="12.542840" />
        <checkpoint x="363.96697" y="-1376.339" z="14.048536" />
        <checkpoint x="536.11694" y="-1259.677" z="16.061025" />
        <checkpoint x="667.07427" y="-1181.936" z="15.914746" />
        <checkpoint x="744.69628" y="-1071.581" z="22.803159" />
        <checkpoint x="797.61126" y="-1032.244" z="24.593059" />
        <checkpoint x="789.08923" y="-932.5900" z="42.252254" />
        <checkpoint x="726.55694" y="-880.0222" z="42.804592" />
        <checkpoint x="682.56451" y="-779.2700" z="29.459491" />
        <checkpoint x="680.19952" y="-608.5637" z="15.840387" />
        <checkpoint x="651.27923" y="-599.1776" z="15.843338" />
        <checkpoint x="1141.9383" y="-947.1838" z="42.315479" />
    </race>
    <race name="LS BSN RoundCurse" laps="3">
        <checkpoint x="1217.6530" y="-940.1641" z="42.307773" />
        <checkpoint x="1123.7413" y="-948.9725" z="42.269706" />
        <checkpoint x="979.60961" y="-965.6911" z="39.191459" />
        <checkpoint x="851.95446" y="-1017.054" z="28.648784" />
        <checkpoint x="755.47583" y="-1064.787" z="23.529474" />
        <checkpoint x="678.30468" y="-1163.189" z="14.833703" />
        <checkpoint x="625.54174" y="-1220.305" z="17.765201" />
        <checkpoint x="629.46673" y="-1394.953" z="12.927477" />
        <checkpoint x="631.32427" y="-1581.776" z="15.181345" />
        <checkpoint x="628.40576" y="-1728.171" z="13.608224" />
        <checkpoint x="715.22515" y="-1768.791" z="13.850166" />
        <checkpoint x="901.55792" y="-1789.053" z="13.076501" />
        <checkpoint x="1019.7053" y="-1814.708" z="13.602714" />
        <checkpoint x="1109.5959" y="-1854.677" z="13.038629" />
        <checkpoint x="1263.5910" y="-1853.115" z="13.038743" />
        <checkpoint x="1316.1601" y="-1814.100" z="13.038824" />
        <checkpoint x="1312.8438" y="-1649.704" z="13.038860" />
        <checkpoint x="1327.8077" y="-1513.046" z="13.044738" />
        <checkpoint x="1355.4653" y="-1420.358" z="13.046265" />
        <checkpoint x="1357.6629" y="-1248.625" z="13.042384" />
        <checkpoint x="1357.6560" y="-1143.557" z="23.302833" />
        <checkpoint x="1367.9836" y="-1038.010" z="25.725984" />
        <checkpoint x="1377.1397" y="-950.4213" z="33.846855" />
        <checkpoint x="1280.8806" y="-924.8446" z="41.456916" />
    </race>
    <race name="LS OutLand Sprint" laps="1">
        <checkpoint x="1160.3939" y="-918.6560" z="42.465240" />
        <checkpoint x="1157.0019" y="-795.2351" z="55.258277" />
        <checkpoint x="1203.7082" y="-631.3811" z="57.238082" />
        <checkpoint x="1246.3906" y="-507.3915" z="26.887847" />
        <checkpoint x="1258.9089" y="-393.4544" z="2.207717" />
        <checkpoint x="1299.6700" y="-372.1007" z="2.580306" />
        <checkpoint x="1462.5644" y="-317.6018" z="3.005954" />
        <checkpoint x="1618.5179" y="-323.8666" z="19.573993" />
        <checkpoint x="1755.8311" y="-344.4118" z="45.956340" />
        <checkpoint x="1845.2015" y="-334.3223" z="41.540046" />
        <checkpoint x="1848.5125" y="-182.0507" z="41.247699" />
        <checkpoint x="1883.4328" y="-46.50413" z="34.511734" />
        <checkpoint x="1904.2949" y="32.838481" z="34.285762" />
        <checkpoint x="1938.1479" y="38.651462" z="33.255466" />
        <checkpoint x="2089.9235" y="41.274353" z="25.992313" />
        <checkpoint x="2292.1152" y="42.523517" z="25.993391" />
        <checkpoint x="2293.2312" y="86.454307" z="25.993846" />
        <checkpoint x="2338.0895" y="89.857940" z="25.985973" />
        <checkpoint x="2345.6887" y="150.90698" z="25.991807" />
        <checkpoint x="2345.2482" y="278.77938" z="25.990188" />
        <checkpoint x="2371.9365" y="283.68383" z="26.689809" />
        <checkpoint x="2495.9990" y="296.57843" z="29.711763" />
        <checkpoint x="2621.8400" y="303.62274" z="36.448070" />
        <checkpoint x="2753.2448" y="184.83140" z="22.019981" />
        <checkpoint x="2755.7695" y="-5.292487" z="32.703262" />
        <checkpoint x="2727.3303" y="-177.5363" z="30.664400" />
        <checkpoint x="2749.9792" y="-406.8216" z="23.555030" />
        <checkpoint x="2874.5517" y="-681.7249" z="10.491843" />
        <checkpoint x="2870.1987" y="-972.9498" z="10.530794" />
        <checkpoint x="2869.2082" y="-1123.125" z="10.539299" />
        <checkpoint x="2832.3249" y="-1137.775" z="13.527680" />
        <checkpoint x="2686.4287" y="-1148.754" z="52.892143" />
        <checkpoint x="2461.0246" y="-1150.901" z="34.945125" />
        <checkpoint x="2371.2016" y="-1151.776" z="27.100851" />
        <checkpoint x="2371.0754" y="-1196.723" z="27.085302" />
        <checkpoint x="2368.8679" y="-1250.473" z="23.492105" />
        <checkpoint x="2413.1528" y="-1256.485" z="23.482677" />
        <checkpoint x="2507.1430" y="-1256.774" z="34.530010" />
        <checkpoint x="2510.0903" y="-1310.839" z="34.343414" />
        <checkpoint x="2510.6574" y="-1388.048" z="28.014926" />
        <checkpoint x="2520.1594" y="-1441.723" z="28.019933" />
        <checkpoint x="2574.6938" y="-1446.166" z="34.629158" />
        <checkpoint x="2642.0378" y="-1446.282" z="29.935258" />
        <checkpoint x="2641.5507" y="-1520.855" z="25.999544" />
        <checkpoint x="2645.6743" y="-1652.943" z="10.363430" />
        <checkpoint x="2740.6926" y="-1657.484" z="12.721129" />
        <checkpoint x="2853.2260" y="-1657.475" z="10.421066" />
        <checkpoint x="2830.6828" y="-1787.989" z="10.530985" />
        <checkpoint x="2823.1330" y="-2026.331" z="10.585911" />
        <checkpoint x="2721.2829" y="-2156.531" z="10.586894" />
        <checkpoint x="2467.0798" y="-2154.813" z="13.155863" />
        <checkpoint x="2346.5791" y="-2209.395" z="13.030946" />
        <checkpoint x="2222.2885" y="-2332.803" z="13.031064" />
        <checkpoint x="2193.1113" y="-2361.443" z="13.030927" />
        <checkpoint x="2149.1352" y="-2336.909" z="13.007496" />
        <checkpoint x="2103.8513" y="-2318.298" z="13.032011" />
        <checkpoint x="2108.2507" y="-2260.199" z="13.038516" />
        <checkpoint x="2136.7036" y="-2227.912" z="13.046034" />
        <checkpoint x="2085.2751" y="-2174.279" z="13.038780" />
        <checkpoint x="1978.9843" y="-2165.468" z="13.032136" />
        <checkpoint x="1774.3867" y="-2164.874" z="13.038328" />
        <checkpoint x="1618.1202" y="-2149.741" z="25.710456" />
        <checkpoint x="1552.5174" y="-2088.405" z="33.718822" />
        <checkpoint x="1530.1422" y="-1913.264" z="14.426164" />
    </race>
    <race name="LS to SF Sprint" laps="1">
        <checkpoint x="1055.6733" y="-1828.608" z="13.218578" />
        <checkpoint x="1001.3265" y="-1791.143" z="13.709095" />
        <checkpoint x="748.78179" y="-1763.143" z="12.520312" />
        <checkpoint x="504.24304" y="-1712.716" z="11.550656" />
        <checkpoint x="275.65142" y="-1685.602" z="7.609097" />
        <checkpoint x="47.070419" y="-1523.778" z="4.765382" />
        <checkpoint x="-122.6309" y="-1465.021" z="2.351177" />
        <checkpoint x="-142.6163" y="-1343.514" z="1.895849" />
        <checkpoint x="-109.6290" y="-1298.716" z="3.535151" />
        <checkpoint x="-60.21875" y="-1366.579" z="11.280732" />
        <checkpoint x="-95.32335" y="-1406.475" z="12.043978" />
        <checkpoint x="-261.6834" y="-1607.392" z="15.520524" />
        <checkpoint x="-347.0911" y="-1820.098" z="20.586044" />
        <checkpoint x="-360.8104" y="-2035.765" z="27.878602" />
        <checkpoint x="-291.4104" y="-2273.221" z="29.687177" />
        <checkpoint x="-165.0480" y="-2420.751" z="35.730373" />
        <checkpoint x="-44.41896" y="-2592.492" z="43.240642" />
        <checkpoint x="-140.1913" y="-2822.549" z="39.386920" />
        <checkpoint x="-418.3751" y="-2776.696" z="65.479675" />
        <checkpoint x="-684.0307" y="-2754.064" z="71.342453" />
        <checkpoint x="-847.4035" y="-2802.267" z="70.522453" />
        <checkpoint x="-1063.994" y="-2853.597" z="67.374290" />
        <checkpoint x="-1325.828" y="-2874.941" z="56.641193" />
        <checkpoint x="-1529.400" y="-2796.479" z="46.670658" />
        <checkpoint x="-1691.885" y="-2665.025" z="47.914348" />
        <checkpoint x="-2025.342" y="-2622.184" z="58.561267" />
        <checkpoint x="-2278.738" y="-2609.724" z="47.636207" />
        <checkpoint x="-2445.644" y="-2413.451" z="31.976511" />
        <checkpoint x="-2447.633" y="-2306.482" z="14.492929" />
        <checkpoint x="-2402.760" y="-2277.702" z="14.384637" />
        <checkpoint x="-2242.921" y="-2195.212" z="35.691040" />
        <checkpoint x="-2104.735" y="-2070.788" z="63.123432" />
        <checkpoint x="-2020.925" y="-1902.952" z="47.144031" />
        <checkpoint x="-1816.629" y="-1717.929" z="28.757574" />
        <checkpoint x="-1586.537" y="-1606.159" z="36.024681" />
        <checkpoint x="-1551.390" y="-1603.684" z="37.390525" />
        <checkpoint x="-1546.617" y="-1558.535" z="37.390304" />
        <checkpoint x="-1605.270" y="-1509.090" z="37.386951" />
        <checkpoint x="-1676.143" y="-1497.532" z="34.824428" />
        <checkpoint x="-1844.688" y="-1410.191" z="37.329452" />
        <checkpoint x="-1973.112" y="-1318.848" z="38.971122" />
        <checkpoint x="-2059.073" y="-1183.101" z="31.881740" />
        <checkpoint x="-2170.740" y="-1017.795" z="33.549346" />
    </race>
    <race name="SFWaterRoundCurse" laps="6">
        <checkpoint x="-2111.766" y="-1006.727" z="31.679384" />
        <checkpoint x="-1985.953" y="-1007.117" z="31.688447" />
        <checkpoint x="-1928.107" y="-1005.055" z="31.628053" />
        <checkpoint x="-1923.429" y="-719.6048" z="31.625820" />
        <checkpoint x="-2152.483" y="-713.0675" z="31.624580" />
        <checkpoint x="-2157.372" y="-1000.607" z="31.628604" />
        <checkpoint x="-2137.707" y="-1005.757" z="31.674554" />
    </race>
    <race name="The SF Round" laps="2">
        <checkpoint x="-2251.704" y="-191.9085" z="34.827556" />
        <checkpoint x="-2183.313" y="-185.9526" z="34.834934" />
        <checkpoint x="-2167.282" y="-78.23165" z="34.827743" />
        <checkpoint x="-2012.106" y="-71.10103" z="34.827045" />
        <checkpoint x="-2005.725" y="32.029899" z="32.469848" />
        <checkpoint x="-2005.385" y="227.53929" z="27.827310" />
        <checkpoint x="-2002.744" y="455.37731" z="34.671695" />
        <checkpoint x="-2002.649" y="719.85009" z="44.952819" />
        <checkpoint x="-1913.957" y="730.16723" z="44.952732" />
        <checkpoint x="-1831.921" y="731.49987" z="38.971015" />
        <checkpoint x="-1745.287" y="728.77075" z="27.478164" />
        <checkpoint x="-1672.675" y="732.90032" z="19.462375" />
        <checkpoint x="-1550.082" y="729.78814" z="6.694588" />
        <checkpoint x="-1538.814" y="841.75610" z="6.693554" />
        <checkpoint x="-1555.151" y="992.66687" z="6.697991" />
        <checkpoint x="-1585.548" y="1130.1130" z="6.694197" />
        <checkpoint x="-1685.191" y="1298.6182" z="6.694944" />
        <checkpoint x="-1816.797" y="1377.4708" z="6.693078" />
        <checkpoint x="-1903.418" y="1329.1816" z="6.694979" />
        <checkpoint x="-2097.738" y="1328.1613" z="6.695181" />
        <checkpoint x="-2263.570" y="1338.2802" z="6.695014" />
        <checkpoint x="-2379.178" y="1374.1245" z="6.767684" />
        <checkpoint x="-2442.508" y="1375.1748" z="6.694789" />
        <checkpoint x="-2455.634" y="1301.1046" z="18.365264" />
        <checkpoint x="-2460.657" y="1219.9809" z="34.731864" />
        <checkpoint x="-2464.536" y="1213.6530" z="34.742588" />
        <checkpoint x="-2574.241" y="1201.7878" z="47.583271" />
        <checkpoint x="-2656.387" y="1203.3863" z="55.085308" />
        <checkpoint x="-2601.491" y="1124.4000" z="55.138145" />
        <checkpoint x="-2606.466" y="1026.6763" z="74.766433" />
        <checkpoint x="-2606.120" y="926.31146" z="65.696128" />
        <checkpoint x="-2607.207" y="879.98986" z="60.450088" />
        <checkpoint x="-2607.883" y="734.04168" z="28.775020" />
        <checkpoint x="-2608.971" y="637.46966" z="14.929037" />
        <checkpoint x="-2608.677" y="499.58331" z="14.116835" />
        <checkpoint x="-2605.464" y="370.49987" z="5.779150" />
        <checkpoint x="-2614.647" y="300.85565" z="3.840416" />
        <checkpoint x="-2692.799" y="292.82327" z="3.923366" />
        <checkpoint x="-2706.491" y="270.49020" z="3.835590" />
        <checkpoint x="-2705.646" y="159.89836" z="3.983709" />
        <checkpoint x="-2705.767" y="81.784057" z="3.963567" />
        <checkpoint x="-2705.877" y="7.434299" z="3.837342" />
        <checkpoint x="-2706.047" y="-72.22492" z="3.949307" />
        <checkpoint x="-2706.418" y="-190.0724" z="3.835609" />
        <checkpoint x="-2678.617" y="-210.0084" z="3.835536" />
        <checkpoint x="-2534.905" y="-210.1095" z="17.678260" />
        <checkpoint x="-2434.338" y="-205.8745" z="34.825691" />
        <checkpoint x="-2421.922" y="-73.91151" z="34.932895" />
        <checkpoint x="-2373.656" y="-76.12172" z="34.912258" />
        <checkpoint x="-2359.843" y="-180.4864" z="34.827865" />
        <checkpoint x="-2293.789" y="-190.9621" z="34.827899" />
    </race>
    <race name="The Largest Round" laps="15">
        <checkpoint x="-2144.917" y="322.66836" z="34.903324" />
        <checkpoint x="-2251.699" y="321.69229" z="34.903182" />
        <checkpoint x="-2250.357" y="232.39683" z="34.897712" />
        <checkpoint x="-2254.844" y="74.666442" z="34.905616" />
        <checkpoint x="-2256.034" y="-61.20194" z="34.905612" />
        <checkpoint x="-2255.774" y="-186.2009" z="34.907054" />
        <checkpoint x="-2215.199" y="-188.7332" z="34.952465" />
        <checkpoint x="-2171.074" y="-171.2611" z="34.905391" />
        <checkpoint x="-2166.225" y="-105.1876" z="34.905597" />
        <checkpoint x="-2165.905" y="-72.46502" z="34.911804" />
        <checkpoint x="-2067.912" y="-72.65990" z="34.905620" />
        <checkpoint x="-2012.713" y="-72.39913" z="34.902923" />
        <checkpoint x="-2005.953" y="9.901778" z="33.111282" />
        <checkpoint x="-2004.981" y="195.51493" z="27.272748" />
        <checkpoint x="-2005.068" y="312.99734" z="34.748519" />
        <checkpoint x="-2098.770" y="319.88317" z="34.749431" />
    </race>
    <race name="MiniSprint" laps="1">
        <checkpoint x="-2033.602" y="-348.4920" z="35.050525" />
        <checkpoint x="-1930.933" y="-337.0523" z="45.643032" />
        <checkpoint x="-1860.169" y="-236.5083" z="47.604881" />
        <checkpoint x="-1888.082" y="-102.9551" z="37.977798" />
        <checkpoint x="-1885.437" y="71.391174" z="37.964061" />
        <checkpoint x="-1858.650" y="191.55647" z="37.696643" />
        <checkpoint x="-1821.633" y="320.91592" z="19.232162" />
        <checkpoint x="-1814.608" y="368.35879" z="16.749366" />
        <checkpoint x="-1853.490" y="416.45111" z="16.741336" />
        <checkpoint x="-1821.505" y="471.34466" z="21.697998" />
        <checkpoint x="-1879.523" y="553.51611" z="34.127971" />
        <checkpoint x="-1897.776" y="629.49572" z="34.749286" />
        <checkpoint x="-1897.074" y="739.85675" z="45.029895" />
        <checkpoint x="-1895.904" y="840.73303" z="34.748619" />
    </race>
    <race name="Untitled Race" laps="1">
        <checkpoint x="-2418.711" y="-75.69853" z="34.926963" />
    </race>
</races>
